sous/__init__.py
sous/cli/__init__.py
sous-0.0.2.dist-info/METADATA
sous-0.0.2.dist-info/WHEEL
sous-0.0.2.dist-info/entry_points.txt
sous-0.0.2.dist-info/licenses/LICENSE.txt
sous-0.0.2.dist-info/RECORD
