Metadata-Version: 2.1
Name: sous
Version: 0.0.2
Project-URL: Documentation, https://github.com/teserak/sous#readme
Project-URL: Issues, https://github.com/teserak/sous/issues
Project-URL: Source, https://github.com/teserak/sous
Author-email: Konrad Rymczak <me@teserak.com>
License-File: LICENSE.txt
Classifier: Development Status :: 4 - Beta
Classifier: Programming Language :: Python
Classifier: Programming Language :: Python :: 3.9
Classifier: Programming Language :: Python :: 3.10
Classifier: Programming Language :: Python :: 3.11
Classifier: Programming Language :: Python :: Implementation :: CPython
Classifier: Programming Language :: Python :: Implementation :: PyPy
Requires-Python: >=3.9
